cost_matrix/__init__.py
cost_matrix/euclidean_matrix.py
cost_matrix/manhattan_matrix.py
cost_matrix/osrm_matrix.py
cost_matrix/spherical_matrix.py
cost_matrix-0.2.0.dist-info/METADATA
cost_matrix-0.2.0.dist-info/WHEEL
cost_matrix-0.2.0.dist-info/RECORD
