Metadata-Version: 2.3
Name: cost-matrix
Version: 0.2.0
Summary: Designed to simplify the creation of cost matrices for optimization problems.
Author: Luan
Author-email: llvdmoraes@gmail.com
Requires-Python: >=3.10,<3.13
Classifier: Programming Language :: Python :: 3
Classifier: Programming Language :: Python :: 3.10
Classifier: Programming Language :: Python :: 3.11
Classifier: Programming Language :: Python :: 3.12
Requires-Dist: numpy (>=1.26.4,<2.0.0)
Requires-Dist: requests (>=2.32.3,<3.0.0)
